<?xml version="1.0" encoding="UTF-8"?>
<vra xmlns="http://www.vraweb.org/vracore4.htm"
     xmlns:xsi="http://www.w3.org/2001/XMLSchema-instance"
     xsi:schemaLocation="http://www.vraweb.org/vracore4.htm http://www.loc.gov/standards/vracore/vra.xsd">

    <work id="photo_la_strada_fighter">
        <agentSet>
            <agent pref="true">
                <name type="personal">Unknown photographer</name>
                <role vocab="aat">photographers</role>
            </agent>
            <agent>
                <name type="personal"
                      vocab="viaf"
                      refid="http://viaf.org/viaf/37021297">Masina, Giulietta</name>
                <role vocab="aat">subjects</role>
            </agent>
            <agent>
                <name type="personal"
                      vocab="viaf"
                      refid="http://viaf.org/viaf/14775572">Quinn, Anthony</name>
                <role vocab="aat">subjects</role>
            </agent>
        </agentSet>

        <dateSet>
            <date type="creation" pref="true">
                <earliestDate>1954</earliestDate>
                <latestDate>1954</latestDate>
            </date>
        </dateSet>

        <descriptionSet>
            <description pref="true">
                Set photograph from Federico Fellini's film La Strada, showing a circus
                performance scene with Giulietta Masina as Gelsomina and Anthony Quinn
                as Zampanò.
            </description>
            <description>
                Vintage gelatin silver print; physical description not fully provided.
                Black and white. Photographic print.
            </description>
        </descriptionSet>

        <locationSet>
            <location pref="true" type="repository">
                <name type="corporate"
                      vocab="viaf"
                      refid="http://viaf.org/viaf/124960346">Cineteca di Bologna</name>
                <refid type="collection">Fondo Fotografie Cineteca</refid>
            </location>
        </locationSet>

        <materialSet>
            <material pref="true" type="medium">Gelatin silver print</material>
        </materialSet>

        <relationSet>
            <relation type="relatedTo">La strada (film, 1954)</relation>
        </relationSet>

        <rightsSet>
            <rights type="copyrighted" pref="true">
                <rightsHolder>Reporters Associati &amp; Archivi</rightsHolder>
                <text>© Reporters Associati &amp; Archivi — All rights reserved</text>
            </rights>
        </rightsSet>

        <sourceSet>
            <source pref="true">
                <name type="corporate"
                      vocab="viaf"
                      refid="http://viaf.org/viaf/124960346">Cineteca di Bologna</name>
                <refid type="accession">26004 - 11</refid>
                <refid type="collection">Fondo Fotografie Cineteca</refid>
            </source>
        </sourceSet>

        <subjectSet>
            <subject pref="true">
                <term type="personalName"
                      vocab="viaf"
                      refid="http://viaf.org/viaf/37021297">Masina, Giulietta</term>
            </subject>
            <subject>
                <term type="personalName"
                      vocab="viaf"
                      refid="http://viaf.org/viaf/14775572">Quinn, Anthony</term>
            </subject>
            <subject>
                <term type="descriptiveTopic">Production still from the film La Strada (1954)</term>
            </subject>
            <subject>
                <term type="genre" vocab="aat">motion picture stills</term>
            </subject>
        </subjectSet>

        <techniqueSet>
            <technique pref="true" vocab="aat">gelatin silver printing</technique>
        </techniqueSet>

        <titleSet>
            <title pref="true">Circus performance scene from La Strada</title>
            <title type="alternative">Gelsomina and Zampanò during a circus act</title>
        </titleSet>

        <worktypeSet>
            <worktype vocab="aat">photographs</worktype>
        </worktypeSet>
    </work>
</vra>